pardon_dance/__init__.py
pardon_dance-1769073.596.343.dist-info/licenses/LICENSE
pardon_dance-1769073.596.343.dist-info/METADATA
pardon_dance-1769073.596.343.dist-info/WHEEL
pardon_dance-1769073.596.343.dist-info/top_level.txt
pardon_dance-1769073.596.343.dist-info/RECORD
