Metadata-Version: 2.4
Name: pardon-dance
Version: 1769073.596.343
Summary: High-quality integration for https://supermaker.ai/video/blog/unlocking-the-magic-of-pardon-dance-the-viral-video-effect-taking-over-social-media/
Home-page: https://supermaker.ai/video/blog/unlocking-the-magic-of-pardon-dance-the-viral-video-effect-taking-over-social-media/
Author: SuperMaker
Classifier: Programming Language :: Python :: 3
Classifier: License :: OSI Approved :: MIT License
Requires-Python: >=3.6
License-File: LICENSE
Dynamic: author
Dynamic: classifier
Dynamic: description
Dynamic: description-content-type
Dynamic: home-page
Dynamic: license-file
Dynamic: requires-python
Dynamic: summary
